langchain_cloudflare/__init__.py
langchain_cloudflare/bindings.py
langchain_cloudflare/chat_models.py
langchain_cloudflare/embeddings.py
langchain_cloudflare/py.typed
langchain_cloudflare/rerankers.py
langchain_cloudflare/vectorstores.py
langchain_cloudflare-0.2.1.dist-info/METADATA
langchain_cloudflare-0.2.1.dist-info/WHEEL
langchain_cloudflare-0.2.1.dist-info/RECORD
