Metadata-Version: 2.4
Name: langchain-cloudflare
Version: 0.2.1
Summary: Langchain Integrations for Cloudflare's WorkersAI and Vectorize
Project-URL: Source Code, https://github.com/cloudflare/langchain-cloudflare/libs/langchain-cloudflare
Project-URL: Release Notes, https://github.com/cloudflare/langchain-cloudflare/blob/main/README.md
License-Expression: MIT
Requires-Python: >=3.10
Requires-Dist: httpx>=0.24.1
Requires-Dist: langchain-core<2.0.0,>=0.3.81
Requires-Dist: pydantic<3.0.0,>=1.10.0
Requires-Dist: requests>=2.31.0
Requires-Dist: sqlalchemy-cloudflare-d1>=0.3.1
Requires-Dist: sqlalchemy>=2.0.0
Requires-Dist: typing-extensions>=4.5.0
Provides-Extra: async
Requires-Dist: greenlet>=3.0.0; extra == 'async'
